openv6ddns/__init__.py
openv6ddns/api.py
openv6ddns/parser.py
openv6ddns-0.1.0.dist-info/METADATA
openv6ddns-0.1.0.dist-info/WHEEL
openv6ddns-0.1.0.dist-info/top_level.txt
openv6ddns-0.1.0.dist-info/RECORD
