Metadata-Version: 2.1
Name: openv6ddns
Version: 0.1.0
Summary: A Python client for Open V6 DDNS API
Home-page: https://github.com/ne53/openv6ddns
Author: ne53
Author-email: neko252222@gmail.com
Classifier: Programming Language :: Python :: 3
Classifier: License :: OSI Approved :: MIT License
Requires-Python: >=3.7
Requires-Dist: requests
